thoi/__init__.py
thoi/collectors.py
thoi/commons.py
thoi/dataset.py
thoi/typing.py
thoi/heuristics/__init__.py
thoi/heuristics/commons.py
thoi/heuristics/greedy.py
thoi/heuristics/scoring.py
thoi/heuristics/simulated_annealing.py
thoi/heuristics/simulated_annealing_multi_order.py
thoi/measures/__init__.py
thoi/measures/constants.py
thoi/measures/gaussian_copula.py
thoi/measures/gaussian_copula_hot_encoded.py
thoi/measures/utils.py
thoi-0.2.37.dist-info/licenses/LICENSE
thoi-0.2.37.dist-info/METADATA
thoi-0.2.37.dist-info/WHEEL
thoi-0.2.37.dist-info/top_level.txt
thoi-0.2.37.dist-info/RECORD
