Metadata-Version: 2.4
Name: thoi
Version: 0.2.37
Summary: Torch - Higher Order Interactions
Home-page: https://github.com/Laouen/THOI
Author: Laouen Mayal Louan Belloli, Ruben Herzog
Author-email: laouen.belloli@gmail.com
Classifier: Development Status :: 4 - Beta
Classifier: Intended Audience :: Science/Research
Classifier: Intended Audience :: Developers
Classifier: Intended Audience :: Education
Classifier: Programming Language :: Python :: 3
Requires-Python: >=3.6
License-File: LICENSE
Requires-Dist: numpy
Requires-Dist: tqdm
Requires-Dist: scipy
Requires-Dist: pandas
Requires-Dist: networkx
Dynamic: author
Dynamic: author-email
Dynamic: classifier
Dynamic: description
Dynamic: description-content-type
Dynamic: home-page
Dynamic: license-file
Dynamic: requires-dist
Dynamic: requires-python
Dynamic: summary
